newtrackon/__init__.py
newtrackon/api/__init__.py
newtrackon/api/client.py
newtrackon/models/__init__.py
newtrackon-0.1.0.dist-info/METADATA
newtrackon-0.1.0.dist-info/WHEEL
newtrackon-0.1.0.dist-info/top_level.txt
newtrackon-0.1.0.dist-info/RECORD
